tscheduler/__int__.py
tscheduler/tscheduler.py
tscheduler-0.0.6.dist-info/LICENSE.txt
tscheduler-0.0.6.dist-info/METADATA
tscheduler-0.0.6.dist-info/WHEEL
tscheduler-0.0.6.dist-info/top_level.txt
tscheduler-0.0.6.dist-info/RECORD
