Metadata-Version: 2.1
Name: tscheduler
Version: 0.0.6
Summary: task scheduler package
Author: The Taibaoui Mohammed
Author-email: taibaoui.mohamed1988@gmail.com
License-File: LICENSE.txt
